.gitignore
CHANGES.txt
INSTALL.txt
LICENSE.txt
README.txt
bootstrap.py
buildout.cfg
setup.py
src/sterch/__init__.py
src/sterch.fields.ip.egg-info/PKG-INFO
src/sterch.fields.ip.egg-info/SOURCES.txt
src/sterch.fields.ip.egg-info/dependency_links.txt
src/sterch.fields.ip.egg-info/namespace_packages.txt
src/sterch.fields.ip.egg-info/requires.txt
src/sterch.fields.ip.egg-info/top_level.txt
src/sterch/fields/__init__.py
src/sterch/fields/ip/__init__.py
src/sterch/fields/ip/address.py
src/sterch/fields/ip/interfaces.py
src/sterch/fields/ip/network.py
src/sterch/fields/ip/tests/__init__.py
src/sterch/fields/ip/tests/test_ipaddressfield.py
src/sterch/fields/ip/tests/test_ipnetworkfield.py